loquitor-1.0.6.dist-info/RECORD
loquitor-1.0.6.dist-info/METADATA
loquitor-1.0.6.dist-info/top_level.txt
loquitor-1.0.6.dist-info/WHEEL
loquitor-1.0.6.dist-info/DESCRIPTION.rst
loquitor-1.0.6.dist-info/metadata.json
home/commandant/.loquitor/SUBSTITUTIONS.txt
loquitor-1.0.6.data/scripts/loquitor
Loquitor/bot.py
Loquitor/__init__.py
Loquitor/skeleton.py
Loquitor/scripts/admin.py
Loquitor/scripts/talk.py
Loquitor/scripts/wotd.py
Loquitor/scripts/substitute.py
Loquitor/scripts/__init__.py
Loquitor/scripts/translate.py
Loquitor/scripts/_parser.py
Loquitor/scripts/search.py
