Metadata-Version: 2.0
Name: loquitor
Version: 1.0.6
Summary: Chatbot for Stack Overflow
Home-page: https://github.com/ralphembree/Loquitor
Author: Ralph Embree
Author-email: ralph.embree@brominator.org
License: UNKNOWN
Platform: UNKNOWN
Requires-Dist: BingTranslator
Requires-Dist: feedparser
Requires-Dist: ChatExchange
